<?xml version="1.0" encoding="UTF-8"?>
<scene id="id269551" GSCVersion="0.10.4" PGFVersion="0.19"><layers><layer id="id112326"><actors><actor id="id907270" prototype="id569657"><attributes><point id="position"><real id="x">286.7890625</real><real id="y">341.841796875</real></point><size id="size"><real id="width">100</real><real id="height">30.70703125</real></size></attributes><aspects/></actor></actors><attributes><text id="name">Background</text><boolean id="scrollable">true</boolean></attributes></layer></layers><attributes><text id="name">Initial Scene</text><real id="time">0</real><size id="size"><real id="width">568</real><real id="height">320</real></size><boolean id="wrapX">false</boolean><boolean id="wrapY">false</boolean><point id="gravity"><real id="x">0</real><real id="y">0</real></point><color id="color"><real id="red">0.16977222263813</real><real id="green">0.81564843654633</real><real id="blue">1</real><real id="alpha">1</real></color><rect id="camera"><point id="origin"><real id="x">0</real><real id="y">0</real></point><size id="size"><real id="width">568</real><real id="height">320</real></size><size id="trackingArea"><real id="width">488</real><real id="height">240</real></size><real id="rotation">0</real></rect><attributes id="autorotate"><boolean id="landscapeLeft">true</boolean><boolean id="portrait">false</boolean><boolean id="landscapeRight">false</boolean><boolean id="portraitUpsideDown">false</boolean></attributes></attributes></scene>
